flake8_unused_arguments.py
flake8_unused_arguments-0.0.13.dist-info/LICENSE
flake8_unused_arguments-0.0.13.dist-info/METADATA
flake8_unused_arguments-0.0.13.dist-info/WHEEL
flake8_unused_arguments-0.0.13.dist-info/entry_points.txt
flake8_unused_arguments-0.0.13.dist-info/top_level.txt
flake8_unused_arguments-0.0.13.dist-info/RECORD
