Metadata-Version: 2.1
Name: flake8-unused-arguments
Version: 0.0.13
Summary: flake8 extension to warn on unused function arguments
Home-page: https://github.com/nhoad/flake8-unused-arguments
Author: Nathan Hoad
Author-email: nathan@hoad.io
License: MIT
Classifier: Framework :: Flake8
Classifier: Environment :: Console
Classifier: Intended Audience :: Developers
Classifier: License :: OSI Approved :: MIT License
Classifier: Programming Language :: Python
Classifier: Programming Language :: Python :: 3
Classifier: Topic :: Software Development :: Libraries :: Python Modules
Classifier: Topic :: Software Development :: Quality Assurance
License-File: LICENSE
Requires-Dist: flake8 (>3.0.0)
